jokeoftheday/__init__.py
jokeoftheday/jokes.txt
jokeoftheday/cli/main.py
joke_for_the_day-0.1.0.dist-info/LICENSE
joke_for_the_day-0.1.0.dist-info/METADATA
joke_for_the_day-0.1.0.dist-info/WHEEL
joke_for_the_day-0.1.0.dist-info/entry_points.txt
joke_for_the_day-0.1.0.dist-info/top_level.txt
joke_for_the_day-0.1.0.dist-info/RECORD
