Metadata-Version: 2.1
Name: joke-for-the-day
Version: 0.1.0
Summary: Joke of the Day Package
Home-page: https://github.com/rohanmohapatra/joke-of-the-day
Author: Rohan Mohapatra
Author-email: rohannmohapatra@gmail.com
License: UNKNOWN
Platform: UNKNOWN
Classifier: Programming Language :: Python :: 3
Classifier: License :: OSI Approved :: MIT License
Classifier: Operating System :: OS Independent
